{
 "creation": "2025-09-04 10:11:00.424554",
 "currency": "BDT",
 "docstatus": 0,
 "doctype": "Number Card",
 "dynamic_filters_json": "{\"from_date\":\"frappe.datetime.month_start(frappe.datetime.get_today())\",\"to_date\":\"frappe.datetime.month_end(frappe.datetime.get_today())\"}",
 "filters_json": "{}",
 "function": "Count",
 "idx": 1,
 "is_public": 0,
 "is_standard": 1,
 "label": "Total VAT Amount",
 "modified": "2025-09-04 16:12:29.646735",
 "modified_by": "Administrator",
 "module": "Vat Challan",
 "name": "Total VAT Amount",
 "owner": "Administrator",
 "report_field": "total_sd_amount",
 "report_function": "Sum",
 "report_name": "VAT Invoice",
 "show_percentage_stats": 1,
 "stats_time_interval": "Daily",
 "type": "Report"
}